interfacy/__init__.py
interfacy/console.py
interfacy/core.py
interfacy/exceptions.py
interfacy/group.py
interfacy/logger.py
interfacy/pipe.py
interfacy/py.typed
interfacy/util.py
interfacy/appearance/__init__.py
interfacy/appearance/colors.py
interfacy/appearance/layout.py
interfacy/appearance/layouts.py
interfacy/argparse_backend/__init__.py
interfacy/argparse_backend/argparser.py
interfacy/argparse_backend/argument_parser.py
interfacy/argparse_backend/help_formatter.py
interfacy/argparse_backend/runner.py
interfacy/cli/__init__.py
interfacy/cli/config.py
interfacy/cli/main.py
interfacy/click_backend/click_parser.py
interfacy/naming/__init__.py
interfacy/naming/abbreviations.py
interfacy/naming/command_naming.py
interfacy/naming/flag_strategy.py
interfacy/naming/name_mapping.py
interfacy/schema/__init__.py
interfacy/schema/builder.py
interfacy/schema/schema.py
interfacy-0.3.11.dist-info/METADATA
interfacy-0.3.11.dist-info/WHEEL
interfacy-0.3.11.dist-info/entry_points.txt
interfacy-0.3.11.dist-info/licenses/LICENSE
interfacy-0.3.11.dist-info/RECORD
