Metadata-Version: 2.4
Name: interfacy
Version: 0.3.11
Summary: CLI framework for building command-line interfaces from Python functions, classes, and class instances
Project-URL: Repository, https://github.com/zigai/interfacy
Project-URL: Issues, https://github.com/zigai/interfacy/issues
Project-URL: Homepage, https://github.com/zigai/interfacy
Author-email: Žiga Ivanšek <ziga.ivansek@gmail.com>
License: MIT License
License-File: LICENSE
Keywords: argparse,cli,cli-builder,cli-framework,cli-generator,command-line,interfacy,type-hints
Classifier: Environment :: Console
Classifier: Intended Audience :: Developers
Classifier: License :: OSI Approved :: MIT License
Classifier: Operating System :: OS Independent
Classifier: Programming Language :: Python
Classifier: Programming Language :: Python :: 3
Classifier: Programming Language :: Python :: 3 :: Only
Classifier: Programming Language :: Python :: 3.10
Classifier: Programming Language :: Python :: 3.11
Classifier: Programming Language :: Python :: 3.12
Classifier: Programming Language :: Python :: 3.13
Classifier: Programming Language :: Python :: 3.14
Classifier: Topic :: Software Development :: Libraries :: Application Frameworks
Classifier: Topic :: Software Development :: Libraries :: Python Modules
Classifier: Topic :: Software Development :: User Interfaces
Classifier: Typing :: Typed
Requires-Python: >=3.10
Requires-Dist: objinspect>=0.4.1
Requires-Dist: stdl>=0.6.8
Requires-Dist: strto>=0.2.6
Requires-Dist: tomli>=2.0; python_version < '3.11'
Requires-Dist: tomlkit>=0.12
Provides-Extra: click
Requires-Dist: click; extra == 'click'
Provides-Extra: dev
Requires-Dist: coverage; extra == 'dev'
Requires-Dist: mypy; extra == 'dev'
Requires-Dist: pre-commit; extra == 'dev'
Requires-Dist: pytest; extra == 'dev'
Requires-Dist: pytest-mock; extra == 'dev'
Requires-Dist: ruff; extra == 'dev'
Provides-Extra: full
Requires-Dist: argcomplete; extra == 'full'
Requires-Dist: click; extra == 'full'
Provides-Extra: test
Requires-Dist: coverage; extra == 'test'
Requires-Dist: pytest; extra == 'test'
Requires-Dist: pytest-mock; extra == 'test'
